dbustiker.py
dbustiker-1.0.0.dist-info/WHEEL
dbustiker-1.0.0.dist-info/METADATA
dbustiker-1.0.0.dist-info/RECORD
